{
    "uid": "f61473f9-130f-42f6-b98d-6c438812c2f6",
    "name": "jetbrains.mps.baseLanguage.unitTest",
    "concepts": [
        {
            "uid": "mps:f61473f9-130f-42f6-b98d-6c438812c2f6/1171931690126",
            "name": "TestMethod",
            "properties": [
                {
                    "uid": "f61473f9-130f-42f6-b98d-6c438812c2f6/1171931690126/1171931690128",
                    "name": "methodName"
                }
            ],
            "children": [
            ],
            "references": [
            ],
            "extends": [
                "jetbrains.mps.baseLanguage.InstanceMethodDeclaration",
                "jetbrains.mps.baseLanguage.unitTest.ITestMethod"
            ]
        },
        {
            "uid": "mps:f61473f9-130f-42f6-b98d-6c438812c2f6/1171931851043",
            "name": "BTestCase",
            "properties": [
                {
                    "uid": "f61473f9-130f-42f6-b98d-6c438812c2f6/1171931851043/1171931851045",
                    "name": "testCaseName"
                }
            ],
            "children": [
                {
                    "uid": "f61473f9-130f-42f6-b98d-6c438812c2f6/1171931851043/1171931851044",
                    "name": "testMethodList",
                    "type": "jetbrains.mps.baseLanguage.unitTest.TestMethodList",
                    "optional": false
                },
                {
                    "uid": "f61473f9-130f-42f6-b98d-6c438812c2f6/1171931851043/8243879142738613219",
                    "name": "beforeTest",
                    "type": "jetbrains.mps.baseLanguage.unitTest.BeforeTest"
                },
                {
                    "uid": "f61473f9-130f-42f6-b98d-6c438812c2f6/1171931851043/8243879142738613220",
                    "name": "afterTest",
                    "type": "jetbrains.mps.baseLanguage.unitTest.AfterTest"
                }
            ],
            "references": [
            ],
            "extends": [
                "jetbrains.mps.baseLanguage.ClassConcept",
                "jetbrains.mps.baseLanguage.unitTest.ITestCase",
                "jetbrains.mps.lang.core.ImplementationPart"
            ]
        },
        {
            "uid": "mps:f61473f9-130f-42f6-b98d-6c438812c2f6/1171931858461",
            "name": "TestMethodList",
            "properties": [
            ],
            "children": [
                {
                    "uid": "f61473f9-130f-42f6-b98d-6c438812c2f6/1171931858461/1171931858462",
                    "name": "testMethod",
                    "type": "jetbrains.mps.baseLanguage.unitTest.TestMethod",
                    "multiple": true
                }
            ],
            "references": [
            ],
            "extends": [
                "jetbrains.mps.lang.core.BaseConcept"
            ]
        },
        {
            "uid": "mps:f61473f9-130f-42f6-b98d-6c438812c2f6/1171978097730",
            "name": "AssertEquals",
            "properties": [
            ],
            "children": [
            ],
            "references": [
            ],
            "extends": [
                "jetbrains.mps.baseLanguage.unitTest.BinaryAssert"
            ]
        },
        {
            "uid": "mps:f61473f9-130f-42f6-b98d-6c438812c2f6/1171981022339",
            "name": "AssertTrue",
            "properties": [
            ],
            "children": [
                {
                    "uid": "f61473f9-130f-42f6-b98d-6c438812c2f6/1171981022339/1171981057159",
                    "name": "condition",
                    "type": "jetbrains.mps.baseLanguage.Expression",
                    "optional": false
                }
            ],
            "references": [
            ],
            "extends": [
                "jetbrains.mps.baseLanguage.Statement",
                "jetbrains.mps.baseLanguage.unitTest.MessageHolder"
            ]
        },
        {
            "uid": "mps:f61473f9-130f-42f6-b98d-6c438812c2f6/1171983834376",
            "name": "AssertFalse",
            "properties": [
            ],
            "children": [
                {
                    "uid": "f61473f9-130f-42f6-b98d-6c438812c2f6/1171983834376/1171983854940",
                    "name": "condition",
                    "type": "jetbrains.mps.baseLanguage.Expression",
                    "optional": false
                }
            ],
            "references": [
            ],
            "extends": [
                "jetbrains.mps.baseLanguage.Statement",
                "jetbrains.mps.baseLanguage.unitTest.MessageHolder"
            ]
        },
        {
            "uid": "mps:f61473f9-130f-42f6-b98d-6c438812c2f6/1171985735491",
            "name": "AssertSame",
            "properties": [
            ],
            "children": [
            ],
            "references": [
            ],
            "extends": [
                "jetbrains.mps.baseLanguage.unitTest.BinaryAssert"
            ]
        },
        {
            "uid": "mps:f61473f9-130f-42f6-b98d-6c438812c2f6/1172017222794",
            "name": "Fail",
            "properties": [
            ],
            "children": [
            ],
            "references": [
            ],
            "extends": [
                "jetbrains.mps.baseLanguage.Statement",
                "jetbrains.mps.baseLanguage.unitTest.MessageHolder"
            ]
        },
        {
            "uid": "mps:f61473f9-130f-42f6-b98d-6c438812c2f6/1172028177041",
            "name": "AssertIsNull",
            "properties": [
            ],
            "children": [
                {
                    "uid": "f61473f9-130f-42f6-b98d-6c438812c2f6/1172028177041/1172028236559",
                    "name": "expression",
                    "type": "jetbrains.mps.baseLanguage.Expression",
                    "optional": false
                }
            ],
            "references": [
            ],
            "extends": [
                "jetbrains.mps.baseLanguage.Statement",
                "jetbrains.mps.baseLanguage.unitTest.MessageHolder"
            ]
        },
        {
            "uid": "mps:f61473f9-130f-42f6-b98d-6c438812c2f6/1172069869612",
            "name": "AssertThrows",
            "properties": [
            ],
            "children": [
                {
                    "uid": "f61473f9-130f-42f6-b98d-6c438812c2f6/1172069869612/1172070029086",
                    "name": "statement",
                    "type": "jetbrains.mps.baseLanguage.Statement",
                    "optional": false
                },
                {
                    "uid": "f61473f9-130f-42f6-b98d-6c438812c2f6/1172069869612/1172070532815",
                    "name": "exceptionType",
                    "type": "jetbrains.mps.baseLanguage.ClassifierType",
                    "optional": false
                }
            ],
            "references": [
            ],
            "extends": [
                "jetbrains.mps.baseLanguage.Statement",
                "jetbrains.mps.baseLanguage.unitTest.MessageHolder"
            ]
        },
        {
            "uid": "mps:f61473f9-130f-42f6-b98d-6c438812c2f6/1172073500303",
            "name": "Message",
            "properties": [
            ],
            "children": [
                {
                    "uid": "f61473f9-130f-42f6-b98d-6c438812c2f6/1172073500303/1172073511101",
                    "name": "message",
                    "type": "jetbrains.mps.baseLanguage.Expression"
                }
            ],
            "references": [
            ],
            "extends": [
                "jetbrains.mps.lang.core.BaseConcept"
            ]
        },
        {
            "uid": "mps:f61473f9-130f-42f6-b98d-6c438812c2f6/1172075514136",
            "name": "MessageHolder",
            "abstract": true,
            "properties": [
            ],
            "children": [
                {
                    "uid": "f61473f9-130f-42f6-b98d-6c438812c2f6/1172075514136/1172075534298",
                    "name": "message",
                    "type": "jetbrains.mps.baseLanguage.unitTest.Message"
                }
            ],
            "references": [
            ],
            "extends": [
            ]
        },
        {
            "uid": "mps:f61473f9-130f-42f6-b98d-6c438812c2f6/1215620452633",
            "name": "ITestable",
            "abstract": true,
            "properties": [
            ],
            "children": [
            ],
            "references": [
            ],
            "extends": [
            ]
        },
        {
            "uid": "mps:f61473f9-130f-42f6-b98d-6c438812c2f6/1216130694486",
            "name": "ITestCase",
            "abstract": true,
            "properties": [
                {
                    "uid": "f61473f9-130f-42f6-b98d-6c438812c2f6/1216130694486/6427619394892729757",
                    "name": "canNotRunInProcess",
                    "type": "BOOLEAN"
                }
            ],
            "children": [
            ],
            "references": [
            ],
            "extends": [
                "jetbrains.mps.baseLanguage.unitTest.ITestable",
                "jetbrains.mps.baseLanguage.IValidIdentifier"
            ]
        },
        {
            "uid": "mps:f61473f9-130f-42f6-b98d-6c438812c2f6/1216134482493",
            "name": "ITestMethod",
            "abstract": true,
            "properties": [
            ],
            "children": [
            ],
            "references": [
            ],
            "extends": [
                "jetbrains.mps.baseLanguage.unitTest.ITestable"
            ]
        },
        {
            "uid": "mps:f61473f9-130f-42f6-b98d-6c438812c2f6/7080278351417106679",
            "name": "AssertIsNotNull",
            "properties": [
            ],
            "children": [
                {
                    "uid": "f61473f9-130f-42f6-b98d-6c438812c2f6/7080278351417106679/7080278351417106681",
                    "name": "expression",
                    "type": "jetbrains.mps.baseLanguage.Expression",
                    "optional": false
                }
            ],
            "references": [
            ],
            "extends": [
                "jetbrains.mps.baseLanguage.Statement",
                "jetbrains.mps.baseLanguage.unitTest.MessageHolder"
            ]
        },
        {
            "uid": "mps:f61473f9-130f-42f6-b98d-6c438812c2f6/8427750732757990717",
            "name": "BinaryAssert",
            "abstract": true,
            "properties": [
            ],
            "children": [
                {
                    "uid": "f61473f9-130f-42f6-b98d-6c438812c2f6/8427750732757990717/8427750732757990724",
                    "name": "expected",
                    "type": "jetbrains.mps.baseLanguage.Expression",
                    "optional": false
                },
                {
                    "uid": "f61473f9-130f-42f6-b98d-6c438812c2f6/8427750732757990717/8427750732757990725",
                    "name": "actual",
                    "type": "jetbrains.mps.baseLanguage.Expression",
                    "optional": false
                }
            ],
            "references": [
            ],
            "extends": [
                "jetbrains.mps.baseLanguage.Statement",
                "jetbrains.mps.baseLanguage.unitTest.MessageHolder"
            ]
        },
        {
            "uid": "mps:f61473f9-130f-42f6-b98d-6c438812c2f6/8243879142738608185",
            "name": "BeforeTest",
            "properties": [
            ],
            "children": [
            ],
            "references": [
            ],
            "extends": [
                "jetbrains.mps.baseLanguage.unitTest.PrepareMethod"
            ]
        },
        {
            "uid": "mps:f61473f9-130f-42f6-b98d-6c438812c2f6/8243879142738613213",
            "name": "AfterTest",
            "properties": [
            ],
            "children": [
            ],
            "references": [
            ],
            "extends": [
                "jetbrains.mps.baseLanguage.unitTest.PrepareMethod"
            ]
        },
        {
            "uid": "mps:f61473f9-130f-42f6-b98d-6c438812c2f6/8243879142738615226",
            "name": "PrepareMethod",
            "abstract": true,
            "properties": [
            ],
            "children": [
            ],
            "references": [
            ],
            "extends": [
                "jetbrains.mps.baseLanguage.ConceptFunction"
            ]
        }
    ]
}